giseo/__init__.py
giseo-1.0.0.dist-info/LICENSE
giseo-1.0.0.dist-info/METADATA
giseo-1.0.0.dist-info/WHEEL
giseo-1.0.0.dist-info/top_level.txt
giseo-1.0.0.dist-info/RECORD
