Metadata-Version: 2.1
Name: giseo
Version: 1.0.0
Summary: Giseo package
Home-page: https://github.com/wigarddev/giseo.py
Author: Yaroslav Wigard
Author-email: rsedrisev@yandex.ru
License: UNKNOWN
Platform: UNKNOWN
Classifier: Programming Language :: Python :: 3
Classifier: License :: OSI Approved :: MIT License
Classifier: Operating System :: OS Independent
License-File: LICENSE
